{
	"name": "ErrorLogFile",
	"properties": {
		"linkedServiceName": {
			"referenceName": "AzureBlobStorage1",
			"type": "LinkedServiceReference"
		},
		"annotations": [],
		"type": "DelimitedText",
		"typeProperties": {
			"location": {
				"type": "AzureBlobStorageLocation",
				"fileName": "ac230785-fa20-451b-6d1f-0b78936fc2f7_0.txt",
				"folderPath": "copyactivity-logs/CopydataExceltoJson/2fd14af0-d812-4a79-afb5-0007a13a9fd7",
				"container": "adflogs"
			},
			"columnDelimiter": ",",
			"escapeChar": "\\",
			"quoteChar": "\""
		},
		"schema": [
			{
				"type": "String"
			},
			{
				"type": "String"
			},
			{
				"type": "String"
			},
			{
				"type": "String"
			},
			{
				"type": "String"
			}
		]
	},
	"type": "Microsoft.DataFactory/factories/datasets"
}